<?xml version="1.0"?>
<Results version="1.0">
<ReportNode type="testrun">
<ReportNode type="Iteration">
<ReportNode type="Action">
<ReportNode type="Iteration">
<ReportNode type="Step">
<Data>
    <Name>LoadFunctionLibrary</Name>
    <Description>LoadFunctionLibrary function passed</Description>
    <StartTime>2023-03-29 18:44:36</StartTime>
    <Result>Passed</Result>
    <Extension>
      <IconKey>151a07b6fd1c4accb7b8fc9f502d0102</IconKey>
      <IsPlainTextNodeName>True</IsPlainTextNodeName>
    </Extension>
    <DeviceInfo />
  </Data>
</ReportNode>
<ReportNode type="Step">
<Data>
    <Name>LoadFunctionLibrary</Name>
    <Description>LoadFunctionLibrary function passed</Description>
    <StartTime>2023-03-29 18:44:36</StartTime>
    <Result>Passed</Result>
    <Extension>
      <IconKey>151a07b6fd1c4accb7b8fc9f502d0102</IconKey>
      <IsPlainTextNodeName>True</IsPlainTextNodeName>
    </Extension>
    <DeviceInfo />
  </Data>
</ReportNode>
<ReportNode type="Step">
<Data>
    <Name>LoadFunctionLibrary</Name>
    <Description>LoadFunctionLibrary function passed</Description>
    <StartTime>2023-03-29 18:44:37</StartTime>
    <Result>Passed</Result>
    <Extension>
      <IconKey>151a07b6fd1c4accb7b8fc9f502d0102</IconKey>
      <IsPlainTextNodeName>True</IsPlainTextNodeName>
    </Extension>
    <DeviceInfo />
  </Data>
</ReportNode>
<ReportNode type="Step">
<Data>
    <Name>LoadFunctionLibrary</Name>
    <Description>LoadFunctionLibrary function passed</Description>
    <StartTime>2023-03-29 18:44:37</StartTime>
    <Result>Passed</Result>
    <Extension>
      <IconKey>151a07b6fd1c4accb7b8fc9f502d0102</IconKey>
      <IsPlainTextNodeName>True</IsPlainTextNodeName>
    </Extension>
    <DeviceInfo />
  </Data>
</ReportNode>
<ReportNode type="Step">
<Data>
    <Name>SystemUtil.Run "chrome",3</Name>
    <StartTime>2023-03-29 18:44:39</StartTime>
    <Result>Done</Result>
    <Extension>
      <IconKey>c93c81abb5bb46e1a3aa423257f7308c</IconKey>
      <IsPlainTextNodeName>True</IsPlainTextNodeName>
    </Extension>
    <DeviceInfo />
  </Data>
</ReportNode>
<ReportNode type="Context">
<ReportNode type="Context">
<ReportNode type="Step">
<Data>
    <Name>Field Username.Exist</Name>
    <Description>"Object exists"</Description>
    <StartTime>2023-03-29 18:44:42</StartTime>
    <Result>Done</Result>
    <Extension>
      <TestObject>
        <Repository>C:\Users\1427\Documents\BNI\DPLK\Lib_Repo_Excel\Repo\RP_Login.tsr</Repository>
        <Path>
          <Object>
            <Type>Browser</Type>
            <Name><![CDATA[DPLK]]></Name>
          </Object>
          <Object>
            <Type>Page</Type>
            <Name><![CDATA[Login]]></Name>
          </Object>
          <Object>
            <Type>WebEdit</Type>
            <Name><![CDATA[Field Username]]></Name>
          </Object>
        </Path>
        <Operation>Exist</Operation>
        <OperationData><![CDATA["Object exists"]]></OperationData>
        <Properties>
          <Property>
            <Name><![CDATA[type]]></Name>
            <Value><![CDATA[text]]></Value>
          </Property>
          <Property>
            <Name><![CDATA[name]]></Name>
            <Value><![CDATA[UserName]]></Value>
          </Property>
          <Property>
            <Name><![CDATA[html tag]]></Name>
            <Value><![CDATA[INPUT]]></Value>
          </Property>
        </Properties>
      </TestObject>
      <IconKey>9c47280e594846cb90c8e7dc5c742661</IconKey>
      <IsPlainTextNodeName>True</IsPlainTextNodeName>
    </Extension>
    <DeviceInfo />
  </Data>
</ReportNode>
<ReportNode type="Step">
<Data>
    <Name>Field Username.Set</Name>
    <Description>"30711"</Description>
    <StartTime>2023-03-29 18:44:45</StartTime>
    <Result>Done</Result>
    <Extension>
      <TestObject>
        <Repository>C:\Users\1427\Documents\BNI\DPLK\Lib_Repo_Excel\Repo\RP_Login.tsr</Repository>
        <Path>
          <Object>
            <Type>Browser</Type>
            <Name><![CDATA[DPLK]]></Name>
          </Object>
          <Object>
            <Type>Page</Type>
            <Name><![CDATA[Login]]></Name>
          </Object>
          <Object>
            <Type>WebEdit</Type>
            <Name><![CDATA[Field Username]]></Name>
          </Object>
        </Path>
        <Operation>Set</Operation>
        <OperationData><![CDATA["30711"]]></OperationData>
        <Properties>
          <Property>
            <Name><![CDATA[type]]></Name>
            <Value><![CDATA[text]]></Value>
          </Property>
          <Property>
            <Name><![CDATA[name]]></Name>
            <Value><![CDATA[UserName]]></Value>
          </Property>
          <Property>
            <Name><![CDATA[html tag]]></Name>
            <Value><![CDATA[INPUT]]></Value>
          </Property>
        </Properties>
      </TestObject>
      <IconKey>9c47280e594846cb90c8e7dc5c742661</IconKey>
      <IsPlainTextNodeName>True</IsPlainTextNodeName>
    </Extension>
    <DeviceInfo />
  </Data>
</ReportNode>
<ReportNode type="Step">
<Data>
    <Name>Field Password.Set</Name>
    <Description>"bni1234"</Description>
    <StartTime>2023-03-29 18:44:45</StartTime>
    <Result>Done</Result>
    <Extension>
      <TestObject>
        <Repository>C:\Users\1427\Documents\BNI\DPLK\Lib_Repo_Excel\Repo\RP_Login.tsr</Repository>
        <Path>
          <Object>
            <Type>Browser</Type>
            <Name><![CDATA[DPLK]]></Name>
          </Object>
          <Object>
            <Type>Page</Type>
            <Name><![CDATA[Login]]></Name>
          </Object>
          <Object>
            <Type>WebEdit</Type>
            <Name><![CDATA[Field Password]]></Name>
          </Object>
        </Path>
        <Operation>Set</Operation>
        <OperationData><![CDATA["bni1234"]]></OperationData>
        <Properties>
          <Property>
            <Name><![CDATA[type]]></Name>
            <Value><![CDATA[password]]></Value>
          </Property>
          <Property>
            <Name><![CDATA[name]]></Name>
            <Value><![CDATA[Password]]></Value>
          </Property>
          <Property>
            <Name><![CDATA[html tag]]></Name>
            <Value><![CDATA[INPUT]]></Value>
          </Property>
        </Properties>
      </TestObject>
      <IconKey>9c47280e594846cb90c8e7dc5c742661</IconKey>
      <IsPlainTextNodeName>True</IsPlainTextNodeName>
    </Extension>
    <DeviceInfo />
  </Data>
</ReportNode>
<ReportNode type="Step">
<Data>
    <Name>Btn Login.Click</Name>
    <Description />
    <StartTime>2023-03-29 18:44:50</StartTime>
    <Result>Done</Result>
    <Extension>
      <TestObject>
        <Repository>C:\Users\1427\Documents\BNI\DPLK\Lib_Repo_Excel\Repo\RP_Login.tsr</Repository>
        <Path>
          <Object>
            <Type>Browser</Type>
            <Name><![CDATA[DPLK]]></Name>
          </Object>
          <Object>
            <Type>Page</Type>
            <Name><![CDATA[Login]]></Name>
          </Object>
          <Object>
            <Type>WebButton</Type>
            <Name><![CDATA[Btn Login]]></Name>
          </Object>
        </Path>
        <Operation>Click</Operation>
        <Properties>
          <Property>
            <Name><![CDATA[type]]></Name>
            <Value><![CDATA[submit]]></Value>
          </Property>
          <Property>
            <Name><![CDATA[name]]></Name>
            <Value><![CDATA[Login]]></Value>
          </Property>
          <Property>
            <Name><![CDATA[html tag]]></Name>
            <Value><![CDATA[INPUT]]></Value>
          </Property>
        </Properties>
      </TestObject>
      <IconKey>35f1f484c62f4fbfbec83c9e6f1a6190</IconKey>
      <IsPlainTextNodeName>True</IsPlainTextNodeName>
    </Extension>
    <DeviceInfo />
  </Data>
</ReportNode>
<ReportNode type="Step">
<Data>
    <Name>Alert Invalid UserName or Password.Exist</Name>
    <Description>"Object does not exist"</Description>
    <StartTime>2023-03-29 18:45:03</StartTime>
    <Result>Done</Result>
    <Extension>
      <TestObject>
        <Repository>C:\Users\1427\Documents\BNI\DPLK\Lib_Repo_Excel\Repo\RP_Login.tsr</Repository>
        <Path>
          <Object>
            <Type>Browser</Type>
            <Name><![CDATA[DPLK]]></Name>
          </Object>
          <Object>
            <Type>Page</Type>
            <Name><![CDATA[Login]]></Name>
          </Object>
          <Object>
            <Type>WebElement</Type>
            <Name><![CDATA[Alert Invalid UserName or Password]]></Name>
          </Object>
        </Path>
        <Operation>Exist</Operation>
        <OperationData><![CDATA["Object does not exist"]]></OperationData>
        <Properties>
          <Property>
            <Name><![CDATA[innertext]]></Name>
            <Value><![CDATA[Invalid UserName or Password]]></Value>
          </Property>
          <Property>
            <Name><![CDATA[html tag]]></Name>
            <Value><![CDATA[DIV]]></Value>
          </Property>
        </Properties>
      </TestObject>
      <IconKey>85d62dfaf67f41a3aa3e91685c66e285</IconKey>
      <IsPlainTextNodeName>True</IsPlainTextNodeName>
    </Extension>
    <DeviceInfo />
  </Data>
</ReportNode>
<Data>
    <Name>Login</Name>
    <Description>Page</Description>
    <StartTime>2023-03-29 18:44:42</StartTime>
    <Duration>26</Duration>
    <Result>Done</Result>
    <Extension>
      <TestObject>
        <Repository>C:\Users\1427\Documents\BNI\DPLK\Lib_Repo_Excel\Repo\RP_Login.tsr</Repository>
        <Path>
          <Object>
            <Type>Browser</Type>
            <Name><![CDATA[DPLK]]></Name>
          </Object>
          <Object>
            <Type>Page</Type>
            <Name><![CDATA[Login]]></Name>
          </Object>
        </Path>
        <OperationData><![CDATA[Page]]></OperationData>
      </TestObject>
      <IconKey>1b2e76635aba42b5b92cadb3e7d3dde2</IconKey>
      <IsPlainTextNodeName>True</IsPlainTextNodeName>
    </Extension>
  </Data>
</ReportNode>
<ReportNode type="Context">
<ReportNode type="Step">
<Data>
    <Name>Alert Notifikasi.Exist</Name>
    <Description>"Object exists"</Description>
    <StartTime>2023-03-29 18:45:08</StartTime>
    <Result>Done</Result>
    <Extension>
      <TestObject>
        <Repository>C:\Users\1427\Documents\BNI\DPLK\Lib_Repo_Excel\Repo\RP_Administration_Dashboard.tsr</Repository>
        <Path>
          <Object>
            <Type>Browser</Type>
            <Name><![CDATA[DPLK]]></Name>
          </Object>
          <Object>
            <Type>Page</Type>
            <Name><![CDATA[Dashboard]]></Name>
          </Object>
          <Object>
            <Type>WebElement</Type>
            <Name><![CDATA[Alert Notifikasi]]></Name>
          </Object>
        </Path>
        <Operation>Exist</Operation>
        <OperationData><![CDATA["Object exists"]]></OperationData>
        <Properties>
          <Property>
            <Name><![CDATA[innertext]]></Name>
            <Value><![CDATA[INFORMASI]]></Value>
          </Property>
          <Property>
            <Name><![CDATA[html tag]]></Name>
            <Value><![CDATA[DIV]]></Value>
          </Property>
          <Property>
            <Name><![CDATA[class]]></Name>
            <Value><![CDATA[modal-header]]></Value>
          </Property>
          <Property>
            <Name><![CDATA[acc_name]]></Name>
            <Value><![CDATA[]]></Value>
          </Property>
        </Properties>
      </TestObject>
      <IconKey>85d62dfaf67f41a3aa3e91685c66e285</IconKey>
      <IsPlainTextNodeName>True</IsPlainTextNodeName>
    </Extension>
    <DeviceInfo />
  </Data>
</ReportNode>
<ReportNode type="Step">
<Data>
    <Name>Btn OK.Click</Name>
    <Description />
    <StartTime>2023-03-29 18:45:08</StartTime>
    <Result>Done</Result>
    <Extension>
      <TestObject>
        <Repository>C:\Users\1427\Documents\BNI\DPLK\Lib_Repo_Excel\Repo\RP_Administration_Dashboard.tsr</Repository>
        <Path>
          <Object>
            <Type>Browser</Type>
            <Name><![CDATA[DPLK]]></Name>
          </Object>
          <Object>
            <Type>Page</Type>
            <Name><![CDATA[Dashboard]]></Name>
          </Object>
          <Object>
            <Type>WebButton</Type>
            <Name><![CDATA[Btn OK]]></Name>
          </Object>
        </Path>
        <Operation>Click</Operation>
        <Properties>
          <Property>
            <Name><![CDATA[type]]></Name>
            <Value><![CDATA[button]]></Value>
          </Property>
          <Property>
            <Name><![CDATA[role]]></Name>
            <Value><![CDATA[]]></Value>
          </Property>
          <Property>
            <Name><![CDATA[name]]></Name>
            <Value><![CDATA[Ok]]></Value>
          </Property>
          <Property>
            <Name><![CDATA[html tag]]></Name>
            <Value><![CDATA[BUTTON]]></Value>
          </Property>
          <Property>
            <Name><![CDATA[acc_name]]></Name>
            <Value><![CDATA[]]></Value>
          </Property>
        </Properties>
      </TestObject>
      <IconKey>35f1f484c62f4fbfbec83c9e6f1a6190</IconKey>
      <IsPlainTextNodeName>True</IsPlainTextNodeName>
    </Extension>
    <DeviceInfo />
  </Data>
</ReportNode>
<Data>
    <Name>Dashboard</Name>
    <Description>Page</Description>
    <StartTime>2023-03-29 18:45:08</StartTime>
    <Duration>2</Duration>
    <Result>Done</Result>
    <Extension>
      <TestObject>
        <Repository>C:\Users\1427\Documents\BNI\DPLK\Lib_Repo_Excel\Repo\RP_Administration_Dashboard.tsr</Repository>
        <Path>
          <Object>
            <Type>Browser</Type>
            <Name><![CDATA[DPLK]]></Name>
          </Object>
          <Object>
            <Type>Page</Type>
            <Name><![CDATA[Dashboard]]></Name>
          </Object>
        </Path>
        <OperationData><![CDATA[Page]]></OperationData>
      </TestObject>
      <IconKey>1b2e76635aba42b5b92cadb3e7d3dde2</IconKey>
      <IsPlainTextNodeName>True</IsPlainTextNodeName>
    </Extension>
  </Data>
</ReportNode>
<ReportNode type="Context">
<ReportNode type="Step">
<Data>
    <Name>Sidebar Menu Setup Kepesertaan Penyelia Settlement.Exist</Name>
    <Description>"Object exists"</Description>
    <StartTime>2023-03-29 18:45:10</StartTime>
    <Result>Done</Result>
    <Extension>
      <TestObject>
        <Repository>C:\Users\1427\Documents\BNI\DPLK\Lib_Repo_Excel\Repo\RP_Sidebar.tsr</Repository>
        <Path>
          <Object>
            <Type>Browser</Type>
            <Name><![CDATA[DPLK]]></Name>
          </Object>
          <Object>
            <Type>Page</Type>
            <Name><![CDATA[Sidebar]]></Name>
          </Object>
          <Object>
            <Type>Link</Type>
            <Name><![CDATA[Sidebar Menu Setup Kepesertaan Penyelia Settlement]]></Name>
          </Object>
        </Path>
        <Operation>Exist</Operation>
        <OperationData><![CDATA["Object exists"]]></OperationData>
        <Properties>
          <Property>
            <Name><![CDATA[text]]></Name>
            <Value><![CDATA[Setup]]></Value>
          </Property>
          <Property>
            <Name><![CDATA[role]]></Name>
            <Value><![CDATA[]]></Value>
          </Property>
          <Property>
            <Name><![CDATA[html tag]]></Name>
            <Value><![CDATA[A]]></Value>
          </Property>
          <Property>
            <Name><![CDATA[acc_name]]></Name>
            <Value><![CDATA[]]></Value>
          </Property>
        </Properties>
      </TestObject>
      <IconKey>5b8e2ab4ab1d46009ee61eb439a9efc6</IconKey>
      <IsPlainTextNodeName>True</IsPlainTextNodeName>
    </Extension>
    <DeviceInfo />
  </Data>
</ReportNode>
<ReportNode type="Step">
<Data>
    <Name>Sidebar Menu Setup Kepesertaan Penyelia Settlement.Click</Name>
    <Description />
    <StartTime>2023-03-29 18:45:10</StartTime>
    <Result>Done</Result>
    <Extension>
      <TestObject>
        <Repository>C:\Users\1427\Documents\BNI\DPLK\Lib_Repo_Excel\Repo\RP_Sidebar.tsr</Repository>
        <Path>
          <Object>
            <Type>Browser</Type>
            <Name><![CDATA[DPLK]]></Name>
          </Object>
          <Object>
            <Type>Page</Type>
            <Name><![CDATA[Sidebar]]></Name>
          </Object>
          <Object>
            <Type>Link</Type>
            <Name><![CDATA[Sidebar Menu Setup Kepesertaan Penyelia Settlement]]></Name>
          </Object>
        </Path>
        <Operation>Click</Operation>
        <Properties>
          <Property>
            <Name><![CDATA[text]]></Name>
            <Value><![CDATA[Setup]]></Value>
          </Property>
          <Property>
            <Name><![CDATA[role]]></Name>
            <Value><![CDATA[]]></Value>
          </Property>
          <Property>
            <Name><![CDATA[html tag]]></Name>
            <Value><![CDATA[A]]></Value>
          </Property>
          <Property>
            <Name><![CDATA[acc_name]]></Name>
            <Value><![CDATA[]]></Value>
          </Property>
        </Properties>
      </TestObject>
      <IconKey>5b8e2ab4ab1d46009ee61eb439a9efc6</IconKey>
      <IsPlainTextNodeName>True</IsPlainTextNodeName>
    </Extension>
    <DeviceInfo />
  </Data>
</ReportNode>
<ReportNode type="Step">
<Data>
    <Name>Sidebar Submenu Without Sub Menu.Exist</Name>
    <Description>"Object exists"</Description>
    <StartTime>2023-03-29 18:45:14</StartTime>
    <Result>Done</Result>
    <Extension>
      <TestObject>
        <Repository>C:\Users\1427\Documents\BNI\DPLK\Lib_Repo_Excel\Repo\RP_Sidebar.tsr</Repository>
        <Path>
          <Object>
            <Type>Browser</Type>
            <Name><![CDATA[DPLK]]></Name>
          </Object>
          <Object>
            <Type>Page</Type>
            <Name><![CDATA[Sidebar]]></Name>
          </Object>
          <Object>
            <Type>Link</Type>
            <Name><![CDATA[Sidebar Submenu Without Sub Menu]]></Name>
          </Object>
        </Path>
        <Operation>Exist</Operation>
        <OperationData><![CDATA["Object exists"]]></OperationData>
        <Properties>
          <Property>
            <Name><![CDATA[text]]></Name>
            <Value><![CDATA[Setup Jenis Program Pensiun]]></Value>
          </Property>
          <Property>
            <Name><![CDATA[html tag]]></Name>
            <Value><![CDATA[A]]></Value>
          </Property>
        </Properties>
      </TestObject>
      <IconKey>5b8e2ab4ab1d46009ee61eb439a9efc6</IconKey>
      <IsPlainTextNodeName>True</IsPlainTextNodeName>
    </Extension>
    <DeviceInfo />
  </Data>
</ReportNode>
<ReportNode type="Step">
<Data>
    <Name>Sidebar Submenu Without Sub Menu.Click</Name>
    <Description />
    <StartTime>2023-03-29 18:45:15</StartTime>
    <Result>Done</Result>
    <Extension>
      <TestObject>
        <Repository>C:\Users\1427\Documents\BNI\DPLK\Lib_Repo_Excel\Repo\RP_Sidebar.tsr</Repository>
        <Path>
          <Object>
            <Type>Browser</Type>
            <Name><![CDATA[DPLK]]></Name>
          </Object>
          <Object>
            <Type>Page</Type>
            <Name><![CDATA[Sidebar]]></Name>
          </Object>
          <Object>
            <Type>Link</Type>
            <Name><![CDATA[Sidebar Submenu Without Sub Menu]]></Name>
          </Object>
        </Path>
        <Operation>Click</Operation>
        <Properties>
          <Property>
            <Name><![CDATA[text]]></Name>
            <Value><![CDATA[Setup Jenis Program Pensiun]]></Value>
          </Property>
          <Property>
            <Name><![CDATA[html tag]]></Name>
            <Value><![CDATA[A]]></Value>
          </Property>
        </Properties>
      </TestObject>
      <IconKey>5b8e2ab4ab1d46009ee61eb439a9efc6</IconKey>
      <IsPlainTextNodeName>True</IsPlainTextNodeName>
    </Extension>
    <DeviceInfo />
  </Data>
</ReportNode>
<Data>
    <Name>Sidebar</Name>
    <Description>Page</Description>
    <StartTime>2023-03-29 18:45:10</StartTime>
    <Duration>9</Duration>
    <Result>Done</Result>
    <Extension>
      <TestObject>
        <Repository>C:\Users\1427\Documents\BNI\DPLK\Lib_Repo_Excel\Repo\RP_Sidebar.tsr</Repository>
        <Path>
          <Object>
            <Type>Browser</Type>
            <Name><![CDATA[DPLK]]></Name>
          </Object>
          <Object>
            <Type>Page</Type>
            <Name><![CDATA[Sidebar]]></Name>
          </Object>
        </Path>
        <OperationData><![CDATA[Page]]></OperationData>
      </TestObject>
      <IconKey>1b2e76635aba42b5b92cadb3e7d3dde2</IconKey>
      <IsPlainTextNodeName>True</IsPlainTextNodeName>
    </Extension>
  </Data>
</ReportNode>
<ReportNode type="Context">
<ReportNode type="Step">
<Data>
    <Name>Field Search Data.Set</Name>
    <Description>"DPPK"</Description>
    <StartTime>2023-03-29 18:45:19</StartTime>
    <Result>Done</Result>
    <Extension>
      <TestObject>
        <Repository>C:\Users\1427\Documents\BNI\DPLK\Lib_Repo_Excel\Repo\RP_Kepesertaan_Setup.tsr</Repository>
        <Path>
          <Object>
            <Type>Browser</Type>
            <Name><![CDATA[DPLK]]></Name>
          </Object>
          <Object>
            <Type>Page</Type>
            <Name><![CDATA[Setup Jenis Program Pensiun]]></Name>
          </Object>
          <Object>
            <Type>WebEdit</Type>
            <Name><![CDATA[Field Search Data]]></Name>
          </Object>
        </Path>
        <Operation>Set</Operation>
        <OperationData><![CDATA["DPPK"]]></OperationData>
        <Properties>
          <Property>
            <Name><![CDATA[type]]></Name>
            <Value><![CDATA[search]]></Value>
          </Property>
          <Property>
            <Name><![CDATA[name]]></Name>
            <Value><![CDATA[WebEdit]]></Value>
          </Property>
          <Property>
            <Name><![CDATA[html tag]]></Name>
            <Value><![CDATA[INPUT]]></Value>
          </Property>
        </Properties>
      </TestObject>
      <IconKey>9c47280e594846cb90c8e7dc5c742661</IconKey>
      <IsPlainTextNodeName>True</IsPlainTextNodeName>
    </Extension>
    <DeviceInfo />
  </Data>
</ReportNode>
<ReportNode type="Step">
<Data>
    <Name>Btn View.Click</Name>
    <Description />
    <StartTime>2023-03-29 18:45:26</StartTime>
    <Result>Done</Result>
    <Extension>
      <TestObject>
        <Repository>C:\Users\1427\Documents\BNI\DPLK\Lib_Repo_Excel\Repo\RP_Kepesertaan_Setup.tsr</Repository>
        <Path>
          <Object>
            <Type>Browser</Type>
            <Name><![CDATA[DPLK]]></Name>
          </Object>
          <Object>
            <Type>Page</Type>
            <Name><![CDATA[Setup Jenis Program Pensiun]]></Name>
          </Object>
          <Object>
            <Type>WebElement</Type>
            <Name><![CDATA[Btn View]]></Name>
          </Object>
        </Path>
        <Operation>Click</Operation>
        <Properties>
          <Property>
            <Name><![CDATA[innertext]]></Name>
            <Value><![CDATA[]]></Value>
          </Property>
          <Property>
            <Name><![CDATA[html tag]]></Name>
            <Value><![CDATA[I]]></Value>
          </Property>
          <Property>
            <Name><![CDATA[class]]></Name>
            <Value><![CDATA[typcn typcn-clipboard]]></Value>
          </Property>
          <Property>
            <Name><![CDATA[acc_name]]></Name>
            <Value><![CDATA[]]></Value>
          </Property>
        </Properties>
      </TestObject>
      <IconKey>85d62dfaf67f41a3aa3e91685c66e285</IconKey>
      <IsPlainTextNodeName>True</IsPlainTextNodeName>
    </Extension>
    <DeviceInfo />
  </Data>
</ReportNode>
<Data>
    <Name>Setup Jenis Program Pensiun</Name>
    <Description>Page</Description>
    <StartTime>2023-03-29 18:45:19</StartTime>
    <Duration>13</Duration>
    <Result>Done</Result>
    <Extension>
      <TestObject>
        <Repository>C:\Users\1427\Documents\BNI\DPLK\Lib_Repo_Excel\Repo\RP_Kepesertaan_Setup.tsr</Repository>
        <Path>
          <Object>
            <Type>Browser</Type>
            <Name><![CDATA[DPLK]]></Name>
          </Object>
          <Object>
            <Type>Page</Type>
            <Name><![CDATA[Setup Jenis Program Pensiun]]></Name>
          </Object>
        </Path>
        <OperationData><![CDATA[Page]]></OperationData>
      </TestObject>
      <IconKey>1b2e76635aba42b5b92cadb3e7d3dde2</IconKey>
      <IsPlainTextNodeName>True</IsPlainTextNodeName>
    </Extension>
  </Data>
</ReportNode>
<ReportNode type="Context">
<ReportNode type="Step">
<Data>
    <Name>Profile.Exist</Name>
    <Description>"Object exists"</Description>
    <StartTime>2023-03-29 18:45:32</StartTime>
    <Result>Done</Result>
    <Extension>
      <TestObject>
        <Repository>C:\Users\1427\Documents\BNI\DPLK\Lib_Repo_Excel\Repo\RP_Administration_Dashboard.tsr</Repository>
        <Path>
          <Object>
            <Type>Browser</Type>
            <Name><![CDATA[DPLK]]></Name>
          </Object>
          <Object>
            <Type>Page</Type>
            <Name><![CDATA[Dashboard]]></Name>
          </Object>
          <Object>
            <Type>Image</Type>
            <Name><![CDATA[Profile]]></Name>
          </Object>
        </Path>
        <Operation>Exist</Operation>
        <OperationData><![CDATA["Object exists"]]></OperationData>
        <Properties>
          <Property>
            <Name><![CDATA[image type]]></Name>
            <Value><![CDATA[Image Link]]></Value>
          </Property>
          <Property>
            <Name><![CDATA[html tag]]></Name>
            <Value><![CDATA[IMG]]></Value>
          </Property>
          <Property>
            <Name><![CDATA[alt]]></Name>
            <Value><![CDATA[]]></Value>
          </Property>
        </Properties>
      </TestObject>
      <IconKey>1198e12f9eb14498bb75f01cc6eb5a49</IconKey>
      <IsPlainTextNodeName>True</IsPlainTextNodeName>
    </Extension>
    <DeviceInfo />
  </Data>
</ReportNode>
<ReportNode type="Step">
<Data>
    <Name>Profile.Click</Name>
    <Description />
    <StartTime>2023-03-29 18:45:32</StartTime>
    <Result>Done</Result>
    <Extension>
      <TestObject>
        <Repository>C:\Users\1427\Documents\BNI\DPLK\Lib_Repo_Excel\Repo\RP_Administration_Dashboard.tsr</Repository>
        <Path>
          <Object>
            <Type>Browser</Type>
            <Name><![CDATA[DPLK]]></Name>
          </Object>
          <Object>
            <Type>Page</Type>
            <Name><![CDATA[Dashboard]]></Name>
          </Object>
          <Object>
            <Type>Image</Type>
            <Name><![CDATA[Profile]]></Name>
          </Object>
        </Path>
        <Operation>Click</Operation>
        <Properties>
          <Property>
            <Name><![CDATA[image type]]></Name>
            <Value><![CDATA[Image Link]]></Value>
          </Property>
          <Property>
            <Name><![CDATA[html tag]]></Name>
            <Value><![CDATA[IMG]]></Value>
          </Property>
          <Property>
            <Name><![CDATA[alt]]></Name>
            <Value><![CDATA[]]></Value>
          </Property>
        </Properties>
      </TestObject>
      <IconKey>1198e12f9eb14498bb75f01cc6eb5a49</IconKey>
      <IsPlainTextNodeName>True</IsPlainTextNodeName>
    </Extension>
    <DeviceInfo />
  </Data>
</ReportNode>
<ReportNode type="Step">
<Data>
    <Name>Btn Logout.Click</Name>
    <Description />
    <StartTime>2023-03-29 18:45:36</StartTime>
    <Result>Done</Result>
    <Extension>
      <TestObject>
        <Repository>C:\Users\1427\Documents\BNI\DPLK\Lib_Repo_Excel\Repo\RP_Administration_Dashboard.tsr</Repository>
        <Path>
          <Object>
            <Type>Browser</Type>
            <Name><![CDATA[DPLK]]></Name>
          </Object>
          <Object>
            <Type>Page</Type>
            <Name><![CDATA[Dashboard]]></Name>
          </Object>
          <Object>
            <Type>WebButton</Type>
            <Name><![CDATA[Btn Logout]]></Name>
          </Object>
        </Path>
        <Operation>Click</Operation>
        <Properties>
          <Property>
            <Name><![CDATA[type]]></Name>
            <Value><![CDATA[submit]]></Value>
          </Property>
          <Property>
            <Name><![CDATA[name]]></Name>
            <Value><![CDATA[Logout]]></Value>
          </Property>
          <Property>
            <Name><![CDATA[html tag]]></Name>
            <Value><![CDATA[BUTTON]]></Value>
          </Property>
        </Properties>
      </TestObject>
      <IconKey>35f1f484c62f4fbfbec83c9e6f1a6190</IconKey>
      <IsPlainTextNodeName>True</IsPlainTextNodeName>
    </Extension>
    <DeviceInfo />
  </Data>
</ReportNode>
<Data>
    <Name>Dashboard</Name>
    <Description>Page</Description>
    <StartTime>2023-03-29 18:45:32</StartTime>
    <Duration>5</Duration>
    <Result>Done</Result>
    <Extension>
      <TestObject>
        <Repository>C:\Users\1427\Documents\BNI\DPLK\Lib_Repo_Excel\Repo\RP_Administration_Dashboard.tsr</Repository>
        <Path>
          <Object>
            <Type>Browser</Type>
            <Name><![CDATA[DPLK]]></Name>
          </Object>
          <Object>
            <Type>Page</Type>
            <Name><![CDATA[Dashboard]]></Name>
          </Object>
        </Path>
        <OperationData><![CDATA[Page]]></OperationData>
      </TestObject>
      <IconKey>1b2e76635aba42b5b92cadb3e7d3dde2</IconKey>
      <IsPlainTextNodeName>True</IsPlainTextNodeName>
    </Extension>
  </Data>
</ReportNode>
<ReportNode type="Context">
<ReportNode type="Step">
<Data>
    <Name>Login.Exist</Name>
    <Description>"Object exists"</Description>
    <StartTime>2023-03-29 18:45:37</StartTime>
    <Result>Done</Result>
    <Extension>
      <TestObject>
        <Repository>C:\Users\1427\Documents\BNI\DPLK\Lib_Repo_Excel\Repo\RP_Login.tsr</Repository>
        <Path>
          <Object>
            <Type>Browser</Type>
            <Name><![CDATA[DPLK]]></Name>
          </Object>
          <Object>
            <Type>Page</Type>
            <Name><![CDATA[Login]]></Name>
          </Object>
          <Object>
            <Type>WebElement</Type>
            <Name><![CDATA[Login]]></Name>
          </Object>
        </Path>
        <Operation>Exist</Operation>
        <OperationData><![CDATA["Object exists"]]></OperationData>
        <Properties>
          <Property>
            <Name><![CDATA[innertext]]></Name>
            <Value><![CDATA[Login]]></Value>
          </Property>
          <Property>
            <Name><![CDATA[html tag]]></Name>
            <Value><![CDATA[SPAN]]></Value>
          </Property>
        </Properties>
      </TestObject>
      <IconKey>85d62dfaf67f41a3aa3e91685c66e285</IconKey>
      <IsPlainTextNodeName>True</IsPlainTextNodeName>
    </Extension>
    <DeviceInfo />
  </Data>
</ReportNode>
<Data>
    <Name>Login</Name>
    <Description>Page</Description>
    <StartTime>2023-03-29 18:45:37</StartTime>
    <Duration>5</Duration>
    <Result>Done</Result>
    <Extension>
      <TestObject>
        <Repository>C:\Users\1427\Documents\BNI\DPLK\Lib_Repo_Excel\Repo\RP_Login.tsr</Repository>
        <Path>
          <Object>
            <Type>Browser</Type>
            <Name><![CDATA[DPLK]]></Name>
          </Object>
          <Object>
            <Type>Page</Type>
            <Name><![CDATA[Login]]></Name>
          </Object>
        </Path>
        <OperationData><![CDATA[Page]]></OperationData>
      </TestObject>
      <IconKey>1b2e76635aba42b5b92cadb3e7d3dde2</IconKey>
      <IsPlainTextNodeName>True</IsPlainTextNodeName>
    </Extension>
  </Data>
</ReportNode>
<Data>
    <Name>DPLK</Name>
    <Description>&lt;table&gt;&lt;tr&gt;&lt;td&gt;&lt;span style="text-align : left; font-size : 12px; "&gt;Local Browser&lt;/span&gt;&lt;/td&gt;&lt;/tr&gt;&lt;/table&gt;</Description>
    <StartTime>2023-03-29 18:44:42</StartTime>
    <Duration>60</Duration>
    <Result>Done</Result>
    <Extension>
      <TestObject>
        <Repository>C:\Users\1427\Documents\BNI\DPLK\Lib_Repo_Excel\Repo\RP_Login.tsr</Repository>
        <Path>
          <Object>
            <Type>Browser</Type>
            <Name><![CDATA[DPLK]]></Name>
          </Object>
        </Path>
        <OperationData><![CDATA[<table><tr><td><span style="text-align : left; font-size : 12px; ">Local Browser</span></td></tr></table>]]></OperationData>
      </TestObject>
      <IconKey>ad2f10d4452c439faa460335d9f8258d</IconKey>
      <IsPlainTextNodeName>True</IsPlainTextNodeName>
    </Extension>
  </Data>
</ReportNode>
<Data>
    <Name>KPS082-001-Kepesertaan-View</Name>
    <Description />
    <StartTime>2023-03-29 18:44:36</StartTime>
    <Duration>66</Duration>
    <Result>Passed</Result>
    <Extension>
      <IconKey>32c42a39c0414850855799fec9d26a22</IconKey>
      <IsPlainTextNodeName>True</IsPlainTextNodeName>
    </Extension>
    <Index>1</Index>
  </Data>
</ReportNode>
<ReportNode type="Iteration">
<ReportNode type="Step">
<Data>
    <Name>LoadFunctionLibrary</Name>
    <Description>LoadFunctionLibrary function passed</Description>
    <StartTime>2023-03-29 18:45:42</StartTime>
    <Result>Passed</Result>
    <Extension>
      <IconKey>151a07b6fd1c4accb7b8fc9f502d0102</IconKey>
      <IsPlainTextNodeName>True</IsPlainTextNodeName>
    </Extension>
    <DeviceInfo />
  </Data>
</ReportNode>
<ReportNode type="Step">
<Data>
    <Name>LoadFunctionLibrary</Name>
    <Description>LoadFunctionLibrary function passed</Description>
    <StartTime>2023-03-29 18:45:42</StartTime>
    <Result>Passed</Result>
    <Extension>
      <IconKey>151a07b6fd1c4accb7b8fc9f502d0102</IconKey>
      <IsPlainTextNodeName>True</IsPlainTextNodeName>
    </Extension>
    <DeviceInfo />
  </Data>
</ReportNode>
<ReportNode type="Step">
<Data>
    <Name>LoadFunctionLibrary</Name>
    <Description>LoadFunctionLibrary function passed</Description>
    <StartTime>2023-03-29 18:45:42</StartTime>
    <Result>Passed</Result>
    <Extension>
      <IconKey>151a07b6fd1c4accb7b8fc9f502d0102</IconKey>
      <IsPlainTextNodeName>True</IsPlainTextNodeName>
    </Extension>
    <DeviceInfo />
  </Data>
</ReportNode>
<ReportNode type="Step">
<Data>
    <Name>LoadFunctionLibrary</Name>
    <Description>LoadFunctionLibrary function passed</Description>
    <StartTime>2023-03-29 18:45:42</StartTime>
    <Result>Passed</Result>
    <Extension>
      <IconKey>151a07b6fd1c4accb7b8fc9f502d0102</IconKey>
      <IsPlainTextNodeName>True</IsPlainTextNodeName>
    </Extension>
    <DeviceInfo />
  </Data>
</ReportNode>
<ReportNode type="Step">
<Data>
    <Name>Stop action iteration replay</Name>
    <Description>Run stopped by user.</Description>
    <StartTime>2023-03-29 18:45:48</StartTime>
    <Result>Information</Result>
    <Extension>
      <IconKey>098df7be59b54e5b9d5ca6636fbdf4e0</IconKey>
      <IsPlainTextNodeName>True</IsPlainTextNodeName>
    </Extension>
  </Data>
</ReportNode>
<Data>
    <Name>KPS082-001-Kepesertaan-View</Name>
    <Description />
    <StartTime>2023-03-29 18:45:42</StartTime>
    <Duration>6</Duration>
    <Result>Passed</Result>
    <Extension>
      <IconKey>32c42a39c0414850855799fec9d26a22</IconKey>
      <IsPlainTextNodeName>True</IsPlainTextNodeName>
    </Extension>
    <Index>2</Index>
    <TestedApplications />
  </Data>
</ReportNode>
<Data>
    <Name>KPS082-001-Kepesertaan-View</Name>
    <Description />
    <StartTime>2023-03-29 18:44:36</StartTime>
    <Duration>72</Duration>
    <Result>Passed</Result>
    <InputParameters />
    <Extension>
      <IconKey>7fdaf81eb9d64e9fb67e6481c8c308c3</IconKey>
      <IsPlainTextNodeName>True</IsPlainTextNodeName>
    </Extension>
  </Data>
</ReportNode>
<Data>
    <Name>Action0</Name>
    <Description />
    <StartTime>2023-03-29 18:44:32</StartTime>
    <Duration>76</Duration>
    <Result>Passed</Result>
    <Extension>
      <IconKey>32c42a39c0414850855799fec9d26a22</IconKey>
      <IsPlainTextNodeName>True</IsPlainTextNodeName>
    </Extension>
    <Index>1</Index>
    <TestedApplications />
  </Data>
</ReportNode>
<Data>
    <Name>DPLKKPS082-001 - Kepesertaan - Setup Jenis Program Pensiun View Detil</Name>
    <ToolName>Micro Focus UFT One</ToolName>
    <ToolVersion>2021</ToolVersion>
    <ToolVersionStringLiteral>2021</ToolVersionStringLiteral>
    <Description />
    <StartTime>2023-03-29 18:44:31</StartTime>
    <Duration>78</Duration>
    <Result>Passed</Result>
    <InputParameters />
    <Extension>
      <ParallelRunnerEnvInfo xmlns:xsi="http://www.w3.org/2001/XMLSchema-instance" xmlns:xsd="http://www.w3.org/2001/XMLSchema">
        <ID />
        <Manufacturer />
        <Model />
        <OsType />
        <OsVersion />
        <DesktopBrowser>Google Chrome</DesktopBrowser>
        <ErrorMessage />
      </ParallelRunnerEnvInfo>
      <IconKey>22ab1899423c409e86809183687edaed</IconKey>
      <IsPlainTextNodeName>True</IsPlainTextNodeName>
    </Extension>
    <Environment>
      <Timezone>+07:00:00</Timezone>
      <Locale>English (Indonesia)</Locale>
      <User>1427</User>
      <CpuInfo>AMD Ryzen 5 5500U with Radeon Graphics         </CpuInfo>
      <NumberOfCores>12</NumberOfCores>
      <TotalMemory>6006</TotalMemory>
      <HostName>DGLQAO-821972-1</HostName>
      <OSInfo>Windows 10 22H2 (x64)</OSInfo>
    </Environment>
    <TestedApplications />
    <Links>
      <Link type="DataTable" reference="Default.xlsx" displayname="Default Data Table" />
    </Links>
  </Data>
</ReportNode>
<GeneralInfo>
    <ResultName>Report</ResultName>
    <RunStartTime>2023-03-29 18:44:31</RunStartTime>
    <Timezone>+07:00:00</Timezone>
    <OrchestrationToolName>Micro Focus UFT One</OrchestrationToolName>
    <OrchestrationToolVersion>2021</OrchestrationToolVersion>
    <OrchestrationToolVersionStringLiteral>2021</OrchestrationToolVersionStringLiteral>
  </GeneralInfo>
</Results>